escape/__init__.py
escape/baked_escaper.py
escape/errors.py
escape/proxy_module.py
escape/py.typed
escape/wrapper.py
escaping-0.0.15.dist-info/LICENSE
escaping-0.0.15.dist-info/METADATA
escaping-0.0.15.dist-info/WHEEL
escaping-0.0.15.dist-info/top_level.txt
escaping-0.0.15.dist-info/RECORD
