Metadata-Version: 2.1
Name: escaping
Version: 0.0.15
Summary: Try not to stand out
Author-email: Evgeniy Blinov <zheni-b@yandex.ru>
Project-URL: Source, https://github.com/pomponchik/escaping
Project-URL: Tracker, https://github.com/pomponchik/escaping/issues
Keywords: exception handling,exception logging,containerized code,safe code,callbacks
Classifier: Operating System :: OS Independent
Classifier: Operating System :: MacOS :: MacOS X
Classifier: Operating System :: Microsoft :: Windows
Classifier: Operating System :: POSIX
Classifier: Operating System :: POSIX :: Linux
Classifier: Programming Language :: Python :: 3.8
Classifier: Programming Language :: Python :: 3.9
Classifier: Programming Language :: Python :: 3.10
Classifier: Programming Language :: Python :: 3.11
Classifier: Programming Language :: Python :: 3.12
Classifier: Programming Language :: Python :: 3.13
Classifier: License :: OSI Approved :: MIT License
Classifier: Intended Audience :: Developers
Classifier: Topic :: Software Development :: Libraries
Classifier: Typing :: Typed
Requires-Python: >=3.8
License-File: LICENSE
Requires-Dist: emptylog>=0.0.9
